pymodaq_plugins_imagingsource/__init__.py
pymodaq_plugins_imagingsource/utils.py
pymodaq_plugins_imagingsource/app/__init__.py
pymodaq_plugins_imagingsource/daq_move_plugins/__init__.py
pymodaq_plugins_imagingsource/daq_viewer_plugins/__init__.py
pymodaq_plugins_imagingsource/daq_viewer_plugins/plugins_0D/__init__.py
pymodaq_plugins_imagingsource/daq_viewer_plugins/plugins_1D/__init__.py
pymodaq_plugins_imagingsource/daq_viewer_plugins/plugins_2D/__init__.py
pymodaq_plugins_imagingsource/daq_viewer_plugins/plugins_2D/daq_2Dviewer_ImagingSource.py
pymodaq_plugins_imagingsource/daq_viewer_plugins/plugins_2D/daq_2Dviewer_ImagingSourceWithLECO.py
pymodaq_plugins_imagingsource/daq_viewer_plugins/plugins_ND/__init__.py
pymodaq_plugins_imagingsource/exporters/__init__.py
pymodaq_plugins_imagingsource/extensions/__init__.py
pymodaq_plugins_imagingsource/hardware/__init__.py
pymodaq_plugins_imagingsource/hardware/imagingsource.py
pymodaq_plugins_imagingsource/models/__init__.py
pymodaq_plugins_imagingsource/resources/__init__.py
pymodaq_plugins_imagingsource/resources/config_DMK-33GR0134_Linux.json
pymodaq_plugins_imagingsource/resources/config_DMK-33GR0134_Windows.json
pymodaq_plugins_imagingsource/resources/config_DMK-42BUC03_Linux.json
pymodaq_plugins_imagingsource/resources/config_DMK-42BUC03_Windows.json
pymodaq_plugins_imagingsource/resources/config_template.toml
pymodaq_plugins_imagingsource/resources/extended_publisher.py
pymodaq_plugins_imagingsource/scanners/__init__.py
pymodaq_plugins_imagingsource-0.0.13.dist-info/METADATA
pymodaq_plugins_imagingsource-0.0.13.dist-info/WHEEL
pymodaq_plugins_imagingsource-0.0.13.dist-info/entry_points.txt
pymodaq_plugins_imagingsource-0.0.13.dist-info/licenses/LICENSE
pymodaq_plugins_imagingsource-0.0.13.dist-info/RECORD
