Metadata-Version: 2.4
Name: pymodaq_plugins_imagingsource
Version: 0.0.13
Summary: PyMoDAQ plugin for interfacing with Imaging Source cameras.
Project-URL: Homepage, https://pymodaq.cnrs.fr
Project-URL: Documentation , https://pymodaq.cnrs.fr
Project-URL: Repository , https://github.com/ccabello99/pymodaq_plugins_imagingsource
Author-email: Christian Cabello <christian.cabello@ip-paris.fr>
Maintainer-email: Christian Cabello <christian.cabello@ip-paris.fr>
License: The MIT License (MIT)
License-File: LICENSE
Classifier: Development Status :: 5 - Production/Stable
Classifier: Intended Audience :: Science/Research
Classifier: License :: OSI Approved :: MIT License
Classifier: Natural Language :: English
Classifier: Operating System :: OS Independent
Classifier: Programming Language :: Python :: 3.8
Classifier: Programming Language :: Python :: 3.9
Classifier: Programming Language :: Python :: 3.10
Classifier: Programming Language :: Python :: 3.11
Classifier: Topic :: Scientific/Engineering :: Human Machine Interfaces
Classifier: Topic :: Scientific/Engineering :: Visualization
Classifier: Topic :: Software Development :: Libraries :: Python Modules
Classifier: Topic :: Software Development :: User Interfaces
Requires-Python: >=3.9
Requires-Dist: h5py
Requires-Dist: imageio
Requires-Dist: imagingcontrol4
Requires-Dist: numpy
Requires-Dist: pymodaq>=4.4.7
Requires-Dist: pywin32; sys_platform == 'win32'
Requires-Dist: uuid6
